lwxutils/__init__.py
lwxutils/train.py
lwxutils-1.2.2.dist-info/LICENSE
lwxutils-1.2.2.dist-info/METADATA
lwxutils-1.2.2.dist-info/WHEEL
lwxutils-1.2.2.dist-info/top_level.txt
lwxutils-1.2.2.dist-info/RECORD
