Metadata-Version: 2.1
Name: lwxutils
Version: 1.2.2
Summary: 工具集合包，摸鱼必备
Author: landwind
Author-email: landwind1180@gmail.com
Classifier: Programming Language :: Python :: 3
Classifier: License :: OSI Approved :: MIT License
Classifier: Operating System :: OS Independent
Requires-Python: >=3
License-File: LICENSE
